uxp/common/__init__.py
uxp/common/azure_provider.py
uxp/common/google_provider.py
uxp/common/hosted_provider.py
uxp/core/__init__.py
uxp/core/_arg_parser.py
uxp/core/_async_helper.py
uxp/core/_component.py
uxp/core/_context.py
uxp/core/_data_accessor.py
uxp/core/_decorators.py
uxp/core/_dot_dict.py
uxp/core/_loader.py
uxp/core/_log_helper.py
uxp/core/_ncall.py
uxp/core/_operation.py
uxp/core/_operation_parser.py
uxp/core/_provider.py
uxp/core/_response.py
uxp/core/_type_converter.py
uxp/core/_yaml_loader.py
uxp/core/constants.py
uxp/core/data_model.py
uxp/core/dependency.py
uxp/core/exceptions.py
uxp/core/main.py
uxp/core/manifest.py
uxp/core/py.typed
uxp/core/registry.yaml
uxp/core/spec.py
uxp/core/time.py
uxp/ql/__init__.py
uxp/ql/_functions.py
uxp/ql/_models.py
uxp/ql/_parser_listener.py
uxp/ql/_ql_parser.py
uxp/ql/_query_processor.py
uxp/ql/exceptions.py
uxp/ql/py.typed
uxp/ql/generated/VerseQLLexer.interp
uxp/ql/generated/VerseQLLexer.py
uxp/ql/generated/VerseQLLexer.tokens
uxp/ql/generated/VerseQLParser.interp
uxp/ql/generated/VerseQLParser.py
uxp/ql/generated/VerseQLParser.tokens
uxp/ql/generated/VerseQLParserListener.py
uxp/ql/grammar/VerseQLLexer.g4
uxp/ql/grammar/VerseQLParser.g4
uxp-0.0.1.dist-info/METADATA
uxp-0.0.1.dist-info/WHEEL
uxp-0.0.1.dist-info/entry_points.txt
uxp-0.0.1.dist-info/licenses/LICENSE
uxp-0.0.1.dist-info/RECORD
